toolkit/__init__.py
toolkit/apps.py
toolkit/tests.py
toolkit/templates/toolkit/forms/field.html
toolkit/templates/toolkit/forms/head.html
toolkit/templates/toolkit/forms/row.html
toolkit/templatetags/__init__.py
toolkit/templatetags/toolkit.py
django_template_toolkit-0.2.0.dist-info/LICENSE
django_template_toolkit-0.2.0.dist-info/METADATA
django_template_toolkit-0.2.0.dist-info/WHEEL
django_template_toolkit-0.2.0.dist-info/top_level.txt
django_template_toolkit-0.2.0.dist-info/RECORD
